vision_stream_toolkit/__init__.py
vision_stream_toolkit/stream.py
vision_stream_toolkit-0.1.0.dist-info/METADATA
vision_stream_toolkit-0.1.0.dist-info/WHEEL
vision_stream_toolkit-0.1.0.dist-info/licenses/LICENSE
vision_stream_toolkit-0.1.0.dist-info/RECORD
