Metadata-Version: 2.4
Name: vision-stream-toolkit
Version: 0.1.0
Summary: Pythonic video streaming made simple - turn OpenCV feeds into clean generators
Project-URL: Homepage, https://github.com/Jenil16/vision-stream-toolkit
Project-URL: Documentation, https://github.com/Jenil16/vision-stream-toolkit#readme
Project-URL: Repository, https://github.com/Jenil16/vision-stream-toolkit
Project-URL: Issues, https://github.com/Jenil16/vision-stream-toolkit/issues
Author-email: Jenil <pjenil2002@gmail.com>
License-Expression: MIT
License-File: LICENSE
Keywords: ai,camera,computer-vision,generator,machine-learning,opencv,streaming,threading,video
Classifier: Development Status :: 4 - Beta
Classifier: Intended Audience :: Developers
Classifier: Intended Audience :: Science/Research
Classifier: License :: OSI Approved :: MIT License
Classifier: Operating System :: OS Independent
Classifier: Programming Language :: Python :: 3
Classifier: Programming Language :: Python :: 3.8
Classifier: Programming Language :: Python :: 3.9
Classifier: Programming Language :: Python :: 3.10
Classifier: Programming Language :: Python :: 3.11
Classifier: Programming Language :: Python :: 3.12
Classifier: Topic :: Multimedia :: Video :: Capture
Classifier: Topic :: Scientific/Engineering :: Artificial Intelligence
Classifier: Topic :: Scientific/Engineering :: Image Processing
Requires-Python: >=3.8
Requires-Dist: numpy>=1.19.0
Requires-Dist: opencv-python>=4.5.0
Provides-Extra: dev
Requires-Dist: black>=23.0.0; extra == 'dev'
Requires-Dist: mypy>=1.0.0; extra == 'dev'
Requires-Dist: pytest-cov>=4.0.0; extra == 'dev'
Requires-Dist: pytest>=7.0.0; extra == 'dev'
Requires-Dist: ruff>=0.1.0; extra == 'dev'
